authen/__init__.py
authen/admin.py
authen/apps.py
authen/models.py
authen/tests.py
authen/urls.py
authen/views.py
authen/migrations/__init__.py
authen/static/authen/css/bootstrap.min.css
authen/static/authen/css/login.css
authen/static/authen/img/bg.jpg
authen/static/authen/img/logo.svg
authen/static/authen/js/bootstrap.min.js
authen/static/authen/js/jquery-3.3.1.slim.min.js
authen/static/authen/js/popper.min.js
authen/templates/authen/base.html
authen/templates/authen/login.html
authen/templates/authen/logout.html
django_authen/__init__.py
django_authen/settings.py
django_authen/urls.py
django_authen/wsgi.py
django_authen-2.0.0.dist-info/METADATA
django_authen-2.0.0.dist-info/RECORD
django_authen-2.0.0.dist-info/WHEEL
django_authen-2.0.0.dist-info/top_level.txt
