Metadata-Version: 2.1
Name: django-authen
Version: 2.0.0
Summary: A simple Django login/logout page w/ bootstrap-4.
Home-page: https://github.com/ozcanyarimdunya/django_authen
Author: Ozcan Yarimdunya
Author-email: ozcanyd@gmail.com
License: BSD License
Platform: UNKNOWN
Classifier: Environment :: Web Environment
Classifier: Framework :: Django
Classifier: Framework :: Django :: 2.0
Classifier: Intended Audience :: Developers
Classifier: License :: OSI Approved :: BSD License
Classifier: Operating System :: OS Independent
Classifier: Programming Language :: Python
Classifier: Programming Language :: Python :: 3.5
Classifier: Programming Language :: Python :: 3.6
Classifier: Topic :: Internet :: WWW/HTTP
Classifier: Topic :: Internet :: WWW/HTTP :: Dynamic Content
Requires-Dist: django-python3-ldap
